math_pkg/__init__.py
math_pkg/__pycache__/__init__.cpython-310.pyc
math_pkg/double_pkg/__init__.py
math_pkg/double_pkg/double_module.py
math_pkg/double_pkg/__pycache__/__init__.cpython-310.pyc
math_pkg/double_pkg/__pycache__/double_module.cpython-310.pyc
math_pkg/square_pkg/__init__.py
math_pkg/square_pkg/square_module.py
math_pkg/square_pkg/__pycache__/__init__.cpython-310.pyc
math_pkg/square_pkg/__pycache__/square.cpython-310.pyc
simplemathpkg-0.6.0.dist-info/METADATA
simplemathpkg-0.6.0.dist-info/WHEEL
simplemathpkg-0.6.0.dist-info/top_level.txt
simplemathpkg-0.6.0.dist-info/RECORD
